{
    "organizations": [],
    "uuid": "355beec83e2e21042c5c9d00de13e3e3ad3873c2",
    "author": "",
    "url": "https://www.reuters.com/article/brief-zafgen-says-co-entered-into-loan-a/brief-zafgen-says-co-entered-into-loan-and-security-agreement-providing-for-term-loan-with-principal-amount-of-20-mln-idUSFWN1P00WE",
    "ord_in_thread": 0,
    "title": "BRIEF-Zafgen Says Co Entered Into Loan And Security Agreement Providing For Term Loan With Principal Amount​ Of $20 Mln",
    "locations": [],
    "highlightText": "",
    "language": "english",
    "persons": [],
    "text": "Jan 5 (Reuters) - Zafgen Inc:\n* ZAFGEN SAYS ‍ON DEC 29, CO ENTERED INTO LOAN AND SECURITY AGREEMENT PROVIDING FOR TERM LOAN WITH PRINCIPAL AMOUNT​ OF $20 MILLION - SEC FILING Source text: [ bit.ly/2Earwn6 ] Further company coverage:\n ",
    "published": "2018-01-06T00:04:00.000+02:00",
    "crawled": "2018-01-06T00:23:18.010+02:00",
    "highlightTitle": "",
    "preprocessed_text": [
        "jan",
        "reuters",
        "zafgen",
        "inc",
        "zafgen",
        "say",
        "dec",
        "co",
        "entered",
        "loan",
        "security",
        "agreement",
        "providing",
        "term",
        "loan",
        "principal",
        "million",
        "sec",
        "filing",
        "source",
        "text",
        "company",
        "coverage"
    ]
}